pyopengenai/__init__.py
pyopengenai/sample_run.py
pyopengenai/setup_local.py
pyopengenai/ai_searcher/__init__.py
pyopengenai/ai_searcher/ai_simple_searcher.py
pyopengenai/custom_ollama/__init__.py
pyopengenai/custom_ollama/custom_ollama.py
pyopengenai/custom_ollama/server.py
pyopengenai/pdf_retreiver/__init__.py
pyopengenai/pdf_retreiver/main.py
pyopengenai/query_master/__init__.py
pyopengenai/query_master/heirarchical_tree.py
pyopengenai/query_master/query_refiner.py
pyopengenai/query_master/search_queries_generator.py
pyopengenai/query_master/search_retriever.py
pyopengenai/query_master/text_splitter.py
pyopengenai/query_master/wordllama_embeds.py
pyopengenai/researcher_ai/__init__.py
pyopengenai/researcher_ai/main/__init__.py
pyopengenai/researcher_ai/main/main.py
pyopengenai/researcher_ai/main/prompts.py
pyopengenai/researcher_ai/main/researcher.py
pyopengenai/researcher_ai/main/semantic_chunker.py
pyopengenai/researcher_ai/main/content_extractor/__init__.py
pyopengenai/researcher_ai/main/content_extractor/main.py
pyopengenai/researcher_ai/main/llm_service/__init__.py
pyopengenai/researcher_ai/main/llm_service/base.py
pyopengenai/researcher_ai/main/parse_url/__init__.py
pyopengenai/researcher_ai/main/parse_url/base.py
pyopengenai/researcher_ai/main/parse_url/html_parser.py
pyopengenai/researcher_ai/main/search_provider/__init__.py
pyopengenai/researcher_ai/main/search_provider/base.py
pyopengenai/researcher_ai/main/search_provider/searcher.py
pyopengenai/researcher_ai/tests/__init__.py
pyopengenai/researcher_ai/tests/url_test.py
pyopengenai/spotlight_llm/__init__.py
pyopengenai/spotlight_llm/prompts.py
pyopengenai/spotlight_llm/spotlight_llm.py
pyopengenai/twitter_scrapper/__init__.py
pyopengenai/twitter_scrapper/scrapper.py
pyopengenai/web_search/__init__.py
pyopengenai/web_search/agent.py
pyopengenai/web_search/embed_search.py
pyopengenai/web_search/html_parser.py
pyopengenai/web_search/optimized_multi_query_searcher.py
pyopengenai/web_search/text_filter.py
pyopengenai-0.3.2.dist-info/LICENSE
pyopengenai-0.3.2.dist-info/METADATA
pyopengenai-0.3.2.dist-info/WHEEL
pyopengenai-0.3.2.dist-info/top_level.txt
pyopengenai-0.3.2.dist-info/RECORD
