Metadata-Version: 2.1
Name: pyopengenai
Version: 0.3.2
Summary: A powerful web content fetcher and processor
Home-page: https://github.com/yourusername/pyopengenai
Author: Kammari Santhosh
Author-email: Your Name <your.email@example.com>
Project-URL: Homepage, https://github.com/yourusername/pyopengenai
Project-URL: Bug Tracker, https://github.com/yourusername/pyopengenai/issues
Classifier: Programming Language :: Python :: 3
Classifier: License :: OSI Approved :: MIT License
Classifier: Operating System :: OS Independent
Requires-Python: >=3.7
License-File: LICENSE
Requires-Dist: langchain-ollama
Requires-Dist: aiohttp
Requires-Dist: selenium==4.25.0
Requires-Dist: webdriver-manager
Requires-Dist: beautifulsoup4
Requires-Dist: requests
Requires-Dist: langchain-text-splitters
Requires-Dist: wordllama
Requires-Dist: fastembed
Requires-Dist: langchain
Requires-Dist: scikit-learn
Requires-Dist: trafilatura
Requires-Dist: nltk
Requires-Dist: transformers
Requires-Dist: sumy
Requires-Dist: nodriver
Requires-Dist: weasyprint
Requires-Dist: markdown
Requires-Dist: pypdf==4.2.0
Requires-Dist: torch
Requires-Dist: urllib3==1.26.19
Requires-Dist: tiktoken
Requires-Dist: PyPDF2
